lore/__init__.py
lore/cli/__init__.py
lore/cli/main.py
lore/cli/commands/__init__.py
lore/cli/commands/blame.py
lore/cli/commands/commit.py
lore/cli/commands/config.py
lore/cli/commands/init.py
lore/cli/commands/search.py
lore/cli/commands/sync.py
lore/core/__init__.py
lore/core/models.py
lore/hooks/__init__.py
lore/hooks/on_stop.py
lore/hooks/post_tool_use.py
lore/hooks/state.py
lore/mcp/__init__.py
lore/mcp/server.py
lore/storage/__init__.py
lore/storage/cloud.py
lore_mcp-1.0.17.dist-info/METADATA
lore_mcp-1.0.17.dist-info/WHEEL
lore_mcp-1.0.17.dist-info/entry_points.txt
lore_mcp-1.0.17.dist-info/licenses/LICENSE
lore_mcp-1.0.17.dist-info/RECORD
