Metadata-Version: 2.4
Name: lore-mcp
Version: 1.0.17
Summary: Version control for AI coding context - Commit your intent, not just your code
Project-URL: Homepage, https://lore-dashboard.jadecon2655.workers.dev
Project-URL: Repository, https://github.com/ctx-stack/lore-mcp
Project-URL: Documentation, https://ctx-stack.github.io/lore-docs/
Author: ctx-stack
License: Apache-2.0
License-File: LICENSE
Keywords: ai,claude,context,intent,lore,mcp,version-control
Classifier: Development Status :: 4 - Beta
Classifier: Intended Audience :: Developers
Classifier: License :: OSI Approved :: Apache Software License
Classifier: Programming Language :: Python :: 3.12
Classifier: Topic :: Software Development :: Version Control
Requires-Python: >=3.12
Requires-Dist: httpx>=0.27.0
Requires-Dist: mcp>=1.0.0
Requires-Dist: nest-asyncio>=1.6.0
Requires-Dist: pydantic>=2.5.0
Requires-Dist: rich>=13.7.0
Requires-Dist: typer>=0.12.0
Provides-Extra: dev
Requires-Dist: pytest-asyncio>=0.23.0; extra == 'dev'
Requires-Dist: pytest-cov>=4.0.0; extra == 'dev'
Requires-Dist: pytest>=8.0.0; extra == 'dev'
Requires-Dist: ruff>=0.1.0; extra == 'dev'
